{
  "uuid": "qudcz37f",
  "href": "",
  "title": "2tyiroc3",
  "emperor": { "uuid": "mezsdqwu", "href": "", "title": "3fwjkgi2" },
  "ancestors": [
    { "uuid": "2j0vebyq", "href": "", "title": "qsq5oknm" },
    { "uuid": "08w1apoy", "href": "", "title": "yieylovr" }
  ],
  "emperor_coins": [
    { "uuid": "32ii73tb", "href": "", "title": "dcvn5la0", "specimens": [] },
    { "uuid": "w3eyopu8", "href": "", "title": "sr2up8sb", "specimens": [] },
    { "uuid": "sjbjzzzs", "href": "", "title": "ouhym074", "specimens": [] },
    { "uuid": "a630kfke", "href": "", "title": "0qqgudfb", "specimens": [] },
    { "uuid": "oiw9pvwf", "href": "", "title": "v6ltyqrs", "specimens": [] },
    { "uuid": "jci0g0n7", "href": "", "title": "as9s48dn", "specimens": [] },
    { "uuid": "1fe5zbxw", "href": "", "title": "rcobqrcp", "specimens": [] },
    { "uuid": "0339flny", "href": "", "title": "vqbk98xe", "specimens": [] },
    { "uuid": "kb88768k", "href": "", "title": "9ko00loh", "specimens": [] },
    { "uuid": "9wo8gtpq", "href": "", "title": "4h4somdh", "specimens": [] },
    { "uuid": "urj0k4a9", "href": "", "title": "qq3ekhlu", "specimens": [] },
    { "uuid": "qmo62yqo", "href": "", "title": "4xdhvjmm", "specimens": [] },
    { "uuid": "phh33jg0", "href": "", "title": "xzewr2vc", "specimens": [] },
    { "uuid": "x0fh2q1w", "href": "", "title": "s8vxbx44", "specimens": [] },
    { "uuid": "4raf79uw", "href": "", "title": "0h91a5zr", "specimens": [] },
    { "uuid": "f1cw0648", "href": "", "title": "smnbzg3h", "specimens": [] },
    { "uuid": "7ix6qv3x", "href": "", "title": "n77w6sh2", "specimens": [] },
    { "uuid": "z7jcgbwk", "href": "", "title": "8fuwshu1", "specimens": [] },
    { "uuid": "b1g1zqxu", "href": "", "title": "xtndo1o5", "specimens": [] },
    { "uuid": "0df0bd2r", "href": "", "title": "ol6lg9to", "specimens": [] },
    { "uuid": "i72ecyo3", "href": "", "title": "078cmy4t", "specimens": [] },
    { "uuid": "54sh3qea", "href": "", "title": "ap7825sv", "specimens": [] },
    { "uuid": "pnhegw3n", "href": "", "title": "pzlupejs", "specimens": [] },
    { "uuid": "yxxgazeh", "href": "", "title": "31m58u2i", "specimens": [] }
  ]
}